agentrun/__init__.py
agentrun/agent_runtime/__client_async_template.py
agentrun/agent_runtime/__endpoint_async_template.py
agentrun/agent_runtime/__init__.py
agentrun/agent_runtime/__runtime_async_template.py
agentrun/agent_runtime/client.py
agentrun/agent_runtime/endpoint.py
agentrun/agent_runtime/model.py
agentrun/agent_runtime/runtime.py
agentrun/agent_runtime/api/__data_async_template.py
agentrun/agent_runtime/api/__init__.py
agentrun/agent_runtime/api/control.py
agentrun/agent_runtime/api/data.py
agentrun/credential/__client_async_template.py
agentrun/credential/__credential_async_template.py
agentrun/credential/__init__.py
agentrun/credential/client.py
agentrun/credential/credential.py
agentrun/credential/model.py
agentrun/credential/api/__init__.py
agentrun/credential/api/control.py
agentrun/integration/__init__.py
agentrun/integration/agentscope/__init__.py
agentrun/integration/agentscope/adapter.py
agentrun/integration/agentscope/builtin.py
agentrun/integration/agentscope/message_adapter.py
agentrun/integration/agentscope/model_adapter.py
agentrun/integration/agentscope/tool_adapter.py
agentrun/integration/builtin/__init__.py
agentrun/integration/builtin/knowledgebase.py
agentrun/integration/builtin/model.py
agentrun/integration/builtin/sandbox.py
agentrun/integration/builtin/toolset.py
agentrun/integration/crewai/__init__.py
agentrun/integration/crewai/adapter.py
agentrun/integration/crewai/builtin.py
agentrun/integration/crewai/model_adapter.py
agentrun/integration/crewai/tool_adapter.py
agentrun/integration/google_adk/__init__.py
agentrun/integration/google_adk/adapter.py
agentrun/integration/google_adk/builtin.py
agentrun/integration/google_adk/message_adapter.py
agentrun/integration/google_adk/model_adapter.py
agentrun/integration/google_adk/tool_adapter.py
agentrun/integration/langchain/__init__.py
agentrun/integration/langchain/adapter.py
agentrun/integration/langchain/builtin.py
agentrun/integration/langchain/message_adapter.py
agentrun_inner_test-0.0.68.dist-info/licenses/LICENSE
agentrun_inner_test-0.0.68.dist-info/METADATA
agentrun_inner_test-0.0.68.dist-info/WHEEL
agentrun_inner_test-0.0.68.dist-info/top_level.txt
agentrun_inner_test-0.0.68.dist-info/RECORD
