Metadata-Version: 2.4
Name: agentrun-inner-test
Version: 0.0.68
Summary: Alibaba Cloud Agent Run SDK
Requires-Python: >=3.10
License-File: LICENSE
Requires-Dist: crcmod>=1.7
Requires-Dist: pydantic>=2.12.4
Requires-Dist: httpx>=0.23.0
Requires-Dist: python-dotenv>=1.2.1
Requires-Dist: typing-extensions>=4.15.0
Requires-Dist: litellm>=1.79.3
Requires-Dist: alibabacloud-devs20230714>=2.4.1
Requires-Dist: pydash>=8.0.5
Requires-Dist: alibabacloud-agentrun20250910>=5.2.0
Requires-Dist: alibabacloud_tea_openapi>=0.4.2
Requires-Dist: alibabacloud_bailian20231229>=2.6.2
Requires-Dist: agentrun-mem0ai>=0.0.6
Provides-Extra: server
Requires-Dist: fastapi>=0.104.0; extra == "server"
Requires-Dist: uvicorn>=0.24.0; extra == "server"
Requires-Dist: ag-ui-protocol>=0.1.10; extra == "server"
Provides-Extra: langchain
Requires-Dist: langchain>=1.0.0; python_version >= "3.10" and extra == "langchain"
Requires-Dist: langchain-openai>=1.0.0; python_version >= "3.10" and extra == "langchain"
Provides-Extra: google-adk
Requires-Dist: google-adk>=1.18.0; extra == "google-adk"
Provides-Extra: agentscope
Requires-Dist: agentscope>=0.1.6; extra == "agentscope"
Provides-Extra: crewai
Requires-Dist: crewai>=1.6.0; extra == "crewai"
Provides-Extra: pydantic-ai
Requires-Dist: pydantic-ai>=1.22.0; python_version >= "3.10" and extra == "pydantic-ai"
Provides-Extra: playwright
Requires-Dist: playwright>=1.40.0; extra == "playwright"
Provides-Extra: mcp
Requires-Dist: mcp>=1.21.2; python_version >= "3.10" and extra == "mcp"
Dynamic: license-file
